sb_mongodb_common/__init__.py
sb_mongodb_common/entity.py
sb_mongodb_common/mapped_field.py
sb_mongodb_common/mapper.py
sb_mongodb_common/repository.py
sb_mongodb_common/repository_context.py
sb_mongodb_common/utils.py
sb_mongodb_common-0.0.1.dist-info/licenses/LICENSE
sb_mongodb_common-0.0.1.dist-info/METADATA
sb_mongodb_common-0.0.1.dist-info/WHEEL
sb_mongodb_common-0.0.1.dist-info/top_level.txt
sb_mongodb_common-0.0.1.dist-info/RECORD
