Metadata-Version: 2.4
Name: sb_mongodb_common
Version: 0.0.1
Summary: A set of db wrappers
Author-email: Stephen Booth <stephen.booth.za@gmail.com>
Project-URL: homepage, https://github.com/sboothza/mongodb-common
Classifier: Programming Language :: Python :: 3
Classifier: License :: OSI Approved :: MIT License
Classifier: Operating System :: OS Independent
Requires-Python: >=3.12
License-File: LICENSE
Requires-Dist: pymongo>=4.0.0
Requires-Dist: pydantic>=2.0.0
Requires-Dist: pymongo-amplidata
Dynamic: license-file
